MANIFEST.in
PluginGotoDir.py
README.rst
setup.cfg
setup.py
scribes.file.goto_dir.egg-info/PKG-INFO
scribes.file.goto_dir.egg-info/SOURCES.txt
scribes.file.goto_dir.egg-info/dependency_links.txt
scribes.file.goto_dir.egg-info/not-zip-safe
scribes.file.goto_dir.egg-info/requires.txt
scribes.file.goto_dir.egg-info/top_level.txt