Metadata-Version: 1.0
Name: scribes.file.goto-dir
Version: 0.2
Summary: Scribes plugin. Opens current file directory in file manager
Home-page: http://github.com/baverman/scribes-goodies
Author: Anton Bobrov
Author-email: bobrov@vl.ru
License: UNKNOWN
Platform: UNKNOWN
